apk_exporter.py
apk_exporter-0.1.1.dist-info/METADATA
apk_exporter-0.1.1.dist-info/WHEEL
apk_exporter-0.1.1.dist-info/entry_points.txt
apk_exporter-0.1.1.dist-info/top_level.txt
apk_exporter-0.1.1.dist-info/RECORD
