Metadata-Version: 2.1
Name: apk_exporter
Version: 0.1.1
Summary: Prometheus exporter for apk-tools
Author-email: fossdd <fossdd@pwned.life>
Maintainer-email: fossdd <fossdd@pwned.life>
License: This is free and unencumbered software released into the public domain.
Project-URL: Repository, https://codeberg.org/fossdd/apk-exporter
Project-URL: Issues, https://codeberg.org/fossdd/apk-exporter/issues
Project-URL: Changelog, https://codeberg.org/fossdd/apk-exporter/releases
Classifier: Development Status :: 3 - Alpha
Classifier: Topic :: System :: Monitoring
Classifier: Intended Audience :: Information Technology
Classifier: Intended Audience :: System Administrators
Classifier: License :: OSI Approved :: The Unlicense (Unlicense)
Classifier: Operating System :: POSIX :: Linux
Classifier: Programming Language :: Python :: 3
Classifier: Programming Language :: Python :: 3.8
Classifier: Programming Language :: Python :: 3.9
Classifier: Programming Language :: Python :: 3.10
Classifier: Programming Language :: Python :: 3.11
Classifier: Programming Language :: Python :: 3.12
Classifier: Programming Language :: Python :: 3.13
Requires-Python: >=3.8
Requires-Dist: prometheus-client
